MANIFEST.in
readme.md
requirements.txt
setup.py
openbts/__init__.py
openbts/codes.py
openbts/components.py
openbts/core.py
openbts/exceptions.py
openbts.egg-info/PKG-INFO
openbts.egg-info/SOURCES.txt
openbts.egg-info/dependency_links.txt
openbts.egg-info/not-zip-safe
openbts.egg-info/pbr.json
openbts.egg-info/requires.txt
openbts.egg-info/top_level.txt