Metadata-Version: 1.1
Name: openbts
Version: 0.1.7
Summary: OpenBTS NodeManager client
Home-page: http://github.com/endaga/openbts-python
Author: Matt Ball
Author-email: matt@endaga.com
License: MIT
Download-URL: https://github.com/endaga/openbts-python/tarball/0.1.7
Platform: UNKNOWN
